[
    {
        "id": 1145054,
        "name": "Rail.STL",
        "size": 18084,
        "url": "https://api.thingiverse.com/files/1145054",
        "public_url": "https://www.thingiverse.com/download:1145054",
        "download_url": "https://api.thingiverse.com/files/1145054/download",
        "threejs_url": "https://cdn.thingiverse.com/threejs_json/e4/80/c8/4c/9c/Rail.js",
        "thumbnail": "https://cdn.thingiverse.com/renders/16/89/30/89/03/Rail_thumb_medium.jpg",
        "default_image": {
            "id": 1887288,
            "url": "https://cdn.thingiverse.com/assets/ae/40/b6/f5/48/Rail.STL",
            "name": "Rail.png",
            "sizes": [
                {
                    "type": "thumb",
                    "size": "large",
                    "url": "https://cdn.thingiverse.com/renders/16/89/30/89/03/Rail_thumb_large.jpg"
                },
                {
                    "type": "thumb",
                    "size": "medium",
                    "url": "https://cdn.thingiverse.com/renders/16/89/30/89/03/Rail_thumb_medium.jpg"
                },
                {
                    "type": "thumb",
                    "size": "small",
                    "url": "https://cdn.thingiverse.com/renders/16/89/30/89/03/Rail_thumb_small.jpg"
                },
                {
                    "type": "thumb",
                    "size": "tiny",
                    "url": "https://cdn.thingiverse.com/renders/16/89/30/89/03/Rail_thumb_tiny.jpg"
                },
                {
                    "type": "preview",
                    "size": "featured",
                    "url": "https://cdn.thingiverse.com/renders/16/89/30/89/03/Rail_preview_featured.jpg"
                },
                {
                    "type": "preview",
                    "size": "card",
                    "url": "https://cdn.thingiverse.com/renders/16/89/30/89/03/Rail_preview_card.jpg"
                },
                {
                    "type": "preview",
                    "size": "large",
                    "url": "https://cdn.thingiverse.com/renders/16/89/30/89/03/Rail_preview_large.jpg"
                },
                {
                    "type": "preview",
                    "size": "medium",
                    "url": "https://cdn.thingiverse.com/renders/16/89/30/89/03/Rail_preview_medium.jpg"
                },
                {
                    "type": "preview",
                    "size": "small",
                    "url": "https://cdn.thingiverse.com/renders/16/89/30/89/03/Rail_preview_small.jpg"
                },
                {
                    "type": "preview",
                    "size": "birdwing",
                    "url": "https://cdn.thingiverse.com/renders/16/89/30/89/03/Rail_preview_birdwing.jpg"
                },
                {
                    "type": "preview",
                    "size": "tiny",
                    "url": "https://cdn.thingiverse.com/renders/16/89/30/89/03/Rail_preview_tiny.jpg"
                },
                {
                    "type": "preview",
                    "size": "tinycard",
                    "url": "https://cdn.thingiverse.com/renders/16/89/30/89/03/Rail_preview_tinycard.jpg"
                },
                {
                    "type": "display",
                    "size": "large",
                    "url": "https://cdn.thingiverse.com/renders/16/89/30/89/03/Rail_display_large.jpg"
                },
                {
                    "type": "display",
                    "size": "medium",
                    "url": "https://cdn.thingiverse.com/renders/16/89/30/89/03/Rail_display_medium.jpg"
                },
                {
                    "type": "display",
                    "size": "small",
                    "url": "https://cdn.thingiverse.com/renders/16/89/30/89/03/Rail_display_small.jpg"
                }
            ],
            "added": "2015-03-07T13:42:51+00:00"
        },
        "date": "2015-03-07 13:38:08",
        "formatted_size": "17 kb",
        "meta_data": [],
        "download_count": 88221,
        "direct_url": "https://cdn.thingiverse.com/assets/ae/40/b6/f5/48/Rail.STL"
    },
    {
        "id": 1145055,
        "name": "Slide_Bearing.STL",
        "size": 28484,
        "url": "https://api.thingiverse.com/files/1145055",
        "public_url": "https://www.thingiverse.com/download:1145055",
        "download_url": "https://api.thingiverse.com/files/1145055/download",
        "threejs_url": "https://cdn.thingiverse.com/threejs_json/15/f8/bd/bc/10/Slide_Bearing.js",
        "thumbnail": "https://cdn.thingiverse.com/renders/5b/ff/16/3e/60/Slide_Bearing_thumb_medium.jpg",
        "default_image": {
            "id": 1887283,
            "url": "https://cdn.thingiverse.com/assets/c0/50/07/f1/91/Slide_Bearing.STL",
            "name": "Slide_Bearing.png",
            "sizes": [
                {
                    "type": "thumb",
                    "size": "large",
                    "url": "https://cdn.thingiverse.com/renders/5b/ff/16/3e/60/Slide_Bearing_thumb_large.jpg"
                },
                {
                    "type": "thumb",
                    "size": "medium",
                    "url": "https://cdn.thingiverse.com/renders/5b/ff/16/3e/60/Slide_Bearing_thumb_medium.jpg"
                },
                {
                    "type": "thumb",
                    "size": "small",
                    "url": "https://cdn.thingiverse.com/renders/5b/ff/16/3e/60/Slide_Bearing_thumb_small.jpg"
                },
                {
                    "type": "thumb",
                    "size": "tiny",
                    "url": "https://cdn.thingiverse.com/renders/5b/ff/16/3e/60/Slide_Bearing_thumb_tiny.jpg"
                },
                {
                    "type": "preview",
                    "size": "featured",
                    "url": "https://cdn.thingiverse.com/renders/5b/ff/16/3e/60/Slide_Bearing_preview_featured.jpg"
                },
                {
                    "type": "preview",
                    "size": "card",
                    "url": "https://cdn.thingiverse.com/renders/5b/ff/16/3e/60/Slide_Bearing_preview_card.jpg"
                },
                {
                    "type": "preview",
                    "size": "large",
                    "url": "https://cdn.thingiverse.com/renders/5b/ff/16/3e/60/Slide_Bearing_preview_large.jpg"
                },
                {
                    "type": "preview",
                    "size": "medium",
                    "url": "https://cdn.thingiverse.com/renders/5b/ff/16/3e/60/Slide_Bearing_preview_medium.jpg"
                },
                {
                    "type": "preview",
                    "size": "small",
                    "url": "https://cdn.thingiverse.com/renders/5b/ff/16/3e/60/Slide_Bearing_preview_small.jpg"
                },
                {
                    "type": "preview",
                    "size": "birdwing",
                    "url": "https://cdn.thingiverse.com/renders/5b/ff/16/3e/60/Slide_Bearing_preview_birdwing.jpg"
                },
                {
                    "type": "preview",
                    "size": "tiny",
                    "url": "https://cdn.thingiverse.com/renders/5b/ff/16/3e/60/Slide_Bearing_preview_tiny.jpg"
                },
                {
                    "type": "preview",
                    "size": "tinycard",
                    "url": "https://cdn.thingiverse.com/renders/5b/ff/16/3e/60/Slide_Bearing_preview_tinycard.jpg"
                },
                {
                    "type": "display",
                    "size": "large",
                    "url": "https://cdn.thingiverse.com/renders/5b/ff/16/3e/60/Slide_Bearing_display_large.jpg"
                },
                {
                    "type": "display",
                    "size": "medium",
                    "url": "https://cdn.thingiverse.com/renders/5b/ff/16/3e/60/Slide_Bearing_display_medium.jpg"
                },
                {
                    "type": "display",
                    "size": "small",
                    "url": "https://cdn.thingiverse.com/renders/5b/ff/16/3e/60/Slide_Bearing_display_small.jpg"
                }
            ],
            "added": "2015-03-07T13:39:07+00:00"
        },
        "date": "2015-03-07 13:38:09",
        "formatted_size": "27 kb",
        "meta_data": [],
        "download_count": 87866,
        "direct_url": "https://cdn.thingiverse.com/assets/c0/50/07/f1/91/Slide_Bearing.STL"
    },
    {
        "id": 1145056,
        "name": "Knob_M8.STL",
        "size": 48484,
        "url": "https://api.thingiverse.com/files/1145056",
        "public_url": "https://www.thingiverse.com/download:1145056",
        "download_url": "https://api.thingiverse.com/files/1145056/download",
        "threejs_url": "https://cdn.thingiverse.com/threejs_json/5a/1c/3d/17/69/Knob_M8.js",
        "thumbnail": "https://cdn.thingiverse.com/renders/13/d4/90/9d/6f/Knob_M8_thumb_medium.jpg",
        "default_image": {
            "id": 1887284,
            "url": "https://cdn.thingiverse.com/assets/04/30/58/b6/73/Knob_M8.STL",
            "name": "Knob_M8.png",
            "sizes": [
                {
                    "type": "thumb",
                    "size": "large",
                    "url": "https://cdn.thingiverse.com/renders/13/d4/90/9d/6f/Knob_M8_thumb_large.jpg"
                },
                {
                    "type": "thumb",
                    "size": "medium",
                    "url": "https://cdn.thingiverse.com/renders/13/d4/90/9d/6f/Knob_M8_thumb_medium.jpg"
                },
                {
                    "type": "thumb",
                    "size": "small",
                    "url": "https://cdn.thingiverse.com/renders/13/d4/90/9d/6f/Knob_M8_thumb_small.jpg"
                },
                {
                    "type": "thumb",
                    "size": "tiny",
                    "url": "https://cdn.thingiverse.com/renders/13/d4/90/9d/6f/Knob_M8_thumb_tiny.jpg"
                },
                {
                    "type": "preview",
                    "size": "featured",
                    "url": "https://cdn.thingiverse.com/renders/13/d4/90/9d/6f/Knob_M8_preview_featured.jpg"
                },
                {
                    "type": "preview",
                    "size": "card",
                    "url": "https://cdn.thingiverse.com/renders/13/d4/90/9d/6f/Knob_M8_preview_card.jpg"
                },
                {
                    "type": "preview",
                    "size": "large",
                    "url": "https://cdn.thingiverse.com/renders/13/d4/90/9d/6f/Knob_M8_preview_large.jpg"
                },
                {
                    "type": "preview",
                    "size": "medium",
                    "url": "https://cdn.thingiverse.com/renders/13/d4/90/9d/6f/Knob_M8_preview_medium.jpg"
                },
                {
                    "type": "preview",
                    "size": "small",
                    "url": "https://cdn.thingiverse.com/renders/13/d4/90/9d/6f/Knob_M8_preview_small.jpg"
                },
                {
                    "type": "preview",
                    "size": "birdwing",
                    "url": "https://cdn.thingiverse.com/renders/13/d4/90/9d/6f/Knob_M8_preview_birdwing.jpg"
                },
                {
                    "type": "preview",
                    "size": "tiny",
                    "url": "https://cdn.thingiverse.com/renders/13/d4/90/9d/6f/Knob_M8_preview_tiny.jpg"
                },
                {
                    "type": "preview",
                    "size": "tinycard",
                    "url": "https://cdn.thingiverse.com/renders/13/d4/90/9d/6f/Knob_M8_preview_tinycard.jpg"
                },
                {
                    "type": "display",
                    "size": "large",
                    "url": "https://cdn.thingiverse.com/renders/13/d4/90/9d/6f/Knob_M8_display_large.jpg"
                },
                {
                    "type": "display",
                    "size": "medium",
                    "url": "https://cdn.thingiverse.com/renders/13/d4/90/9d/6f/Knob_M8_display_medium.jpg"
                },
                {
                    "type": "display",
                    "size": "small",
                    "url": "https://cdn.thingiverse.com/renders/13/d4/90/9d/6f/Knob_M8_display_small.jpg"
                }
            ],
            "added": "2015-03-07T13:39:08+00:00"
        },
        "date": "2015-03-07 13:38:09",
        "formatted_size": "47 kb",
        "meta_data": [],
        "download_count": 87939,
        "direct_url": "https://cdn.thingiverse.com/assets/04/30/58/b6/73/Knob_M8.STL"
    },
    {
        "id": 1145057,
        "name": "Master_Body.STL",
        "size": 77584,
        "url": "https://api.thingiverse.com/files/1145057",
        "public_url": "https://www.thingiverse.com/download:1145057",
        "download_url": "https://api.thingiverse.com/files/1145057/download",
        "threejs_url": "https://cdn.thingiverse.com/threejs_json/d9/7e/53/a1/ce/Master_Body.js",
        "thumbnail": "https://cdn.thingiverse.com/renders/51/85/37/a2/67/Master_Body_thumb_medium.jpg",
        "default_image": {
            "id": 1887282,
            "url": "https://cdn.thingiverse.com/assets/16/0e/7c/64/b0/Master_Body.STL",
            "name": "Master_Body.png",
            "sizes": [
                {
                    "type": "thumb",
                    "size": "large",
                    "url": "https://cdn.thingiverse.com/renders/51/85/37/a2/67/Master_Body_thumb_large.jpg"
                },
                {
                    "type": "thumb",
                    "size": "medium",
                    "url": "https://cdn.thingiverse.com/renders/51/85/37/a2/67/Master_Body_thumb_medium.jpg"
                },
                {
                    "type": "thumb",
                    "size": "small",
                    "url": "https://cdn.thingiverse.com/renders/51/85/37/a2/67/Master_Body_thumb_small.jpg"
                },
                {
                    "type": "thumb",
                    "size": "tiny",
                    "url": "https://cdn.thingiverse.com/renders/51/85/37/a2/67/Master_Body_thumb_tiny.jpg"
                },
                {
                    "type": "preview",
                    "size": "featured",
                    "url": "https://cdn.thingiverse.com/renders/51/85/37/a2/67/Master_Body_preview_featured.jpg"
                },
                {
                    "type": "preview",
                    "size": "card",
                    "url": "https://cdn.thingiverse.com/renders/51/85/37/a2/67/Master_Body_preview_card.jpg"
                },
                {
                    "type": "preview",
                    "size": "large",
                    "url": "https://cdn.thingiverse.com/renders/51/85/37/a2/67/Master_Body_preview_large.jpg"
                },
                {
                    "type": "preview",
                    "size": "medium",
                    "url": "https://cdn.thingiverse.com/renders/51/85/37/a2/67/Master_Body_preview_medium.jpg"
                },
                {
                    "type": "preview",
                    "size": "small",
                    "url": "https://cdn.thingiverse.com/renders/51/85/37/a2/67/Master_Body_preview_small.jpg"
                },
                {
                    "type": "preview",
                    "size": "birdwing",
                    "url": "https://cdn.thingiverse.com/renders/51/85/37/a2/67/Master_Body_preview_birdwing.jpg"
                },
                {
                    "type": "preview",
                    "size": "tiny",
                    "url": "https://cdn.thingiverse.com/renders/51/85/37/a2/67/Master_Body_preview_tiny.jpg"
                },
                {
                    "type": "preview",
                    "size": "tinycard",
                    "url": "https://cdn.thingiverse.com/renders/51/85/37/a2/67/Master_Body_preview_tinycard.jpg"
                },
                {
                    "type": "display",
                    "size": "large",
                    "url": "https://cdn.thingiverse.com/renders/51/85/37/a2/67/Master_Body_display_large.jpg"
                },
                {
                    "type": "display",
                    "size": "medium",
                    "url": "https://cdn.thingiverse.com/renders/51/85/37/a2/67/Master_Body_display_medium.jpg"
                },
                {
                    "type": "display",
                    "size": "small",
                    "url": "https://cdn.thingiverse.com/renders/51/85/37/a2/67/Master_Body_display_small.jpg"
                }
            ],
            "added": "2015-03-07T13:39:02+00:00"
        },
        "date": "2015-03-07 13:38:09",
        "formatted_size": "75 kb",
        "meta_data": [],
        "download_count": 88260,
        "direct_url": "https://cdn.thingiverse.com/assets/16/0e/7c/64/b0/Master_Body.STL"
    },
    {
        "id": 1145092,
        "name": "Angular__Piece.STL",
        "size": 18684,
        "url": "https://api.thingiverse.com/files/1145092",
        "public_url": "https://www.thingiverse.com/download:1145092",
        "download_url": "https://api.thingiverse.com/files/1145092/download",
        "threejs_url": "https://cdn.thingiverse.com/threejs_json/37/32/0c/77/05/Angular__Piece.js",
        "thumbnail": "https://cdn.thingiverse.com/renders/9d/4d/66/59/db/Angular__Piece_thumb_medium.jpg",
        "default_image": {
            "id": 1887353,
            "url": "https://cdn.thingiverse.com/assets/2d/22/29/69/73/Angular__Piece.STL",
            "name": "Angular__Piece.png",
            "sizes": [
                {
                    "type": "thumb",
                    "size": "large",
                    "url": "https://cdn.thingiverse.com/renders/9d/4d/66/59/db/Angular__Piece_thumb_large.jpg"
                },
                {
                    "type": "thumb",
                    "size": "medium",
                    "url": "https://cdn.thingiverse.com/renders/9d/4d/66/59/db/Angular__Piece_thumb_medium.jpg"
                },
                {
                    "type": "thumb",
                    "size": "small",
                    "url": "https://cdn.thingiverse.com/renders/9d/4d/66/59/db/Angular__Piece_thumb_small.jpg"
                },
                {
                    "type": "thumb",
                    "size": "tiny",
                    "url": "https://cdn.thingiverse.com/renders/9d/4d/66/59/db/Angular__Piece_thumb_tiny.jpg"
                },
                {
                    "type": "preview",
                    "size": "featured",
                    "url": "https://cdn.thingiverse.com/renders/9d/4d/66/59/db/Angular__Piece_preview_featured.jpg"
                },
                {
                    "type": "preview",
                    "size": "card",
                    "url": "https://cdn.thingiverse.com/renders/9d/4d/66/59/db/Angular__Piece_preview_card.jpg"
                },
                {
                    "type": "preview",
                    "size": "large",
                    "url": "https://cdn.thingiverse.com/renders/9d/4d/66/59/db/Angular__Piece_preview_large.jpg"
                },
                {
                    "type": "preview",
                    "size": "medium",
                    "url": "https://cdn.thingiverse.com/renders/9d/4d/66/59/db/Angular__Piece_preview_medium.jpg"
                },
                {
                    "type": "preview",
                    "size": "small",
                    "url": "https://cdn.thingiverse.com/renders/9d/4d/66/59/db/Angular__Piece_preview_small.jpg"
                },
                {
                    "type": "preview",
                    "size": "birdwing",
                    "url": "https://cdn.thingiverse.com/renders/9d/4d/66/59/db/Angular__Piece_preview_birdwing.jpg"
                },
                {
                    "type": "preview",
                    "size": "tiny",
                    "url": "https://cdn.thingiverse.com/renders/9d/4d/66/59/db/Angular__Piece_preview_tiny.jpg"
                },
                {
                    "type": "preview",
                    "size": "tinycard",
                    "url": "https://cdn.thingiverse.com/renders/9d/4d/66/59/db/Angular__Piece_preview_tinycard.jpg"
                },
                {
                    "type": "display",
                    "size": "large",
                    "url": "https://cdn.thingiverse.com/renders/9d/4d/66/59/db/Angular__Piece_display_large.jpg"
                },
                {
                    "type": "display",
                    "size": "medium",
                    "url": "https://cdn.thingiverse.com/renders/9d/4d/66/59/db/Angular__Piece_display_medium.jpg"
                },
                {
                    "type": "display",
                    "size": "small",
                    "url": "https://cdn.thingiverse.com/renders/9d/4d/66/59/db/Angular__Piece_display_small.jpg"
                }
            ],
            "added": "2015-03-07T14:06:13+00:00"
        },
        "date": "2015-03-07 14:05:16",
        "formatted_size": "18 kb",
        "meta_data": [],
        "download_count": 87905,
        "direct_url": "https://cdn.thingiverse.com/assets/2d/22/29/69/73/Angular__Piece.STL"
    },
    {
        "id": 1206809,
        "name": "Slide_bearing_reinforced.STL",
        "size": 28484,
        "url": "https://api.thingiverse.com/files/1206809",
        "public_url": "https://www.thingiverse.com/download:1206809",
        "download_url": "https://api.thingiverse.com/files/1206809/download",
        "threejs_url": "https://cdn.thingiverse.com/threejs_json/4e/09/b4/bd/f1/Slide_bearing_reinforced.js",
        "thumbnail": "https://cdn.thingiverse.com/renders/e4/73/c4/48/b2/Slide_bearing_reinforced_thumb_medium.jpg",
        "default_image": {
            "id": 1984880,
            "url": "https://cdn.thingiverse.com/assets/00/6f/f5/1d/75/Slide_bearing_reinforced.STL",
            "name": "Slide_bearing_reinforced.png",
            "sizes": [
                {
                    "type": "thumb",
                    "size": "large",
                    "url": "https://cdn.thingiverse.com/renders/e4/73/c4/48/b2/Slide_bearing_reinforced_thumb_large.jpg"
                },
                {
                    "type": "thumb",
                    "size": "medium",
                    "url": "https://cdn.thingiverse.com/renders/e4/73/c4/48/b2/Slide_bearing_reinforced_thumb_medium.jpg"
                },
                {
                    "type": "thumb",
                    "size": "small",
                    "url": "https://cdn.thingiverse.com/renders/e4/73/c4/48/b2/Slide_bearing_reinforced_thumb_small.jpg"
                },
                {
                    "type": "thumb",
                    "size": "tiny",
                    "url": "https://cdn.thingiverse.com/renders/e4/73/c4/48/b2/Slide_bearing_reinforced_thumb_tiny.jpg"
                },
                {
                    "type": "preview",
                    "size": "featured",
                    "url": "https://cdn.thingiverse.com/renders/e4/73/c4/48/b2/Slide_bearing_reinforced_preview_featured.jpg"
                },
                {
                    "type": "preview",
                    "size": "card",
                    "url": "https://cdn.thingiverse.com/renders/e4/73/c4/48/b2/Slide_bearing_reinforced_preview_card.jpg"
                },
                {
                    "type": "preview",
                    "size": "large",
                    "url": "https://cdn.thingiverse.com/renders/e4/73/c4/48/b2/Slide_bearing_reinforced_preview_large.jpg"
                },
                {
                    "type": "preview",
                    "size": "medium",
                    "url": "https://cdn.thingiverse.com/renders/e4/73/c4/48/b2/Slide_bearing_reinforced_preview_medium.jpg"
                },
                {
                    "type": "preview",
                    "size": "small",
                    "url": "https://cdn.thingiverse.com/renders/e4/73/c4/48/b2/Slide_bearing_reinforced_preview_small.jpg"
                },
                {
                    "type": "preview",
                    "size": "birdwing",
                    "url": "https://cdn.thingiverse.com/renders/e4/73/c4/48/b2/Slide_bearing_reinforced_preview_birdwing.jpg"
                },
                {
                    "type": "preview",
                    "size": "tiny",
                    "url": "https://cdn.thingiverse.com/renders/e4/73/c4/48/b2/Slide_bearing_reinforced_preview_tiny.jpg"
                },
                {
                    "type": "preview",
                    "size": "tinycard",
                    "url": "https://cdn.thingiverse.com/renders/e4/73/c4/48/b2/Slide_bearing_reinforced_preview_tinycard.jpg"
                },
                {
                    "type": "display",
                    "size": "large",
                    "url": "https://cdn.thingiverse.com/renders/e4/73/c4/48/b2/Slide_bearing_reinforced_display_large.jpg"
                },
                {
                    "type": "display",
                    "size": "medium",
                    "url": "https://cdn.thingiverse.com/renders/e4/73/c4/48/b2/Slide_bearing_reinforced_display_medium.jpg"
                },
                {
                    "type": "display",
                    "size": "small",
                    "url": "https://cdn.thingiverse.com/renders/e4/73/c4/48/b2/Slide_bearing_reinforced_display_small.jpg"
                }
            ],
            "added": "2015-04-01T21:14:27+00:00"
        },
        "date": "2015-04-01 21:13:30",
        "formatted_size": "27 kb",
        "meta_data": [],
        "download_count": 87636,
        "direct_url": "https://cdn.thingiverse.com/assets/00/6f/f5/1d/75/Slide_bearing_reinforced.STL"
    }
]